dateversioning/__init__.py
poetry_commit_date_versioning-0.4.0.dist-info/METADATA
poetry_commit_date_versioning-0.4.0.dist-info/WHEEL
poetry_commit_date_versioning-0.4.0.dist-info/entry_points.txt
poetry_commit_date_versioning-0.4.0.dist-info/RECORD
