Metadata-Version: 2.1
Name: poetry-commit-date-versioning
Version: 0.4.0
Summary: A Poetry plugin that observes the current git commit to build a date-based version number
Author: Matt McShane
Author-email: matt@mattmcshane.com
Requires-Python: >=3.9,<4.0
Classifier: Programming Language :: Python :: 3
Classifier: Programming Language :: Python :: 3.9
Classifier: Programming Language :: Python :: 3.10
Classifier: Programming Language :: Python :: 3.11
Classifier: Programming Language :: Python :: 3.12
Requires-Dist: dulwich (>=0.21.7,<0.22.0)
Requires-Dist: poetry (>=1.7,<2.0)
